{
  "entries": {
    "tap": {
      "homebrew/core": {
        "revision": "601b74fcc2ed6ba07672c2412ac9490270096c5c"
      },
      "homebrew/bundle": {
        "revision": "79503805c4c557f842a49c3e0ec4021fac0813be"
      },
      "homebrew/services": {
        "revision": "64347a3a5761db1b392f1b30b045aeb4592e17a9"
      },
      "homebrew/cask-fonts": {
        "revision": "ab8b8f1457df8ba66ee0ff23f8ef799b077562f1"
      },
      "homebrew/cask-versions": {
        "revision": "09b98129765ad98cfcd45c4c4ec104cb64728810"
      }
    },
    "brew": {
      "curl": {
        "version": "7.69.1",
        "bottle": {
          "cellar": ":any",
          "prefix": "/home/linuxbrew/.linuxbrew",
          "files": {
            "catalina": {
              "url": "https://linuxbrew.bintray.com/bottles/curl-7.69.1.catalina.bottle.tar.gz",
              "sha256": "400500fede02f9335bd38c16786b2bbf5e601e358dfac8c21e363d2a8fdd8fac"
            },
            "mojave": {
              "url": "https://linuxbrew.bintray.com/bottles/curl-7.69.1.mojave.bottle.tar.gz",
              "sha256": "f082c275f9af1e8e93be12b63a1aff659ba6efa48c8528a97e26c9858a6f95b6"
            },
            "high_sierra": {
              "url": "https://linuxbrew.bintray.com/bottles/curl-7.69.1.high_sierra.bottle.tar.gz",
              "sha256": "ad023093c252799a4c60646a149bfe14ffa6984817cf463a6f0e98f6551057fe"
            },
            "x86_64_linux": {
              "url": "https://linuxbrew.bintray.com/bottles/curl-7.69.1.x86_64_linux.bottle.tar.gz",
              "sha256": "423eeb5fdd77207e6fb9fb214c08d7da2305a8d528319a487c3599a8900f8f6f"
            }
          }
        }
      },
      "git": {
        "version": "2.26.1_1",
        "bottle": {
          "cellar": "/home/linuxbrew/.linuxbrew/Cellar",
          "prefix": "/home/linuxbrew/.linuxbrew",
          "files": {
            "catalina": {
              "url": "https://linuxbrew.bintray.com/bottles/git-2.26.1_1.catalina.bottle.tar.gz",
              "sha256": "8cfa59f2744db5265337345fca63c77bfa89c1485af954c9368c0a76e7bdadff"
            },
            "mojave": {
              "url": "https://linuxbrew.bintray.com/bottles/git-2.26.1_1.mojave.bottle.tar.gz",
              "sha256": "e2451e6df655f129fa7cfcdf182efa8f44d3bfbd34441c9dd23d20d82b9b3fe9"
            },
            "high_sierra": {
              "url": "https://linuxbrew.bintray.com/bottles/git-2.26.1_1.high_sierra.bottle.tar.gz",
              "sha256": "fd29207ec2ad82f05f0244c6156a4f267023c660ed315d65f5619fbeeb489045"
            },
            "x86_64_linux": {
              "url": "https://linuxbrew.bintray.com/bottles/git-2.26.1_1.x86_64_linux.bottle.tar.gz",
              "sha256": "b11fac41b9ed5491b3175284fe9e046ae1a170b36b6ab478aeecffceb3ce84b6"
            }
          }
        }
      },
      "gcc": {
        "version": "5.5.0_7",
        "bottle": {
          "cellar": ":any",
          "prefix": "/home/linuxbrew/.linuxbrew",
          "files": {
            "catalina": {
              "url": "https://linuxbrew.bintray.com/bottles/gcc-5.5.0_7.catalina.bottle.tar.gz",
              "sha256": "57e53d66ad43fe05b5a2f93d6a7cfd472713ac03e9d9c9d0d0187cdc7a273153"
            },
            "mojave": {
              "url": "https://linuxbrew.bintray.com/bottles/gcc-5.5.0_7.mojave.bottle.tar.gz",
              "sha256": "de8319322428721741a0dc41dfdf2eece80e0215a7a4a861e0e206a9bfbca583"
            },
            "high_sierra": {
              "url": "https://linuxbrew.bintray.com/bottles/gcc-5.5.0_7.high_sierra.bottle.tar.gz",
              "sha256": "e50b9cfee063619515a8f164485b3f730077f21b49b7bb30cc5a600ddf577a83"
            },
            "x86_64_linux": {
              "url": "https://linuxbrew.bintray.com/bottles/gcc-5.5.0_7.x86_64_linux.bottle.tar.gz",
              "sha256": "8cae5e1f1e2074f46bfeda826313afb7b823879d190f27dbcd6b00fbfd8daedd"
            }
          }
        }
      },
      "neovim": {
        "version": "0.4.3_1",
        "bottle": {
          "cellar": "/home/linuxbrew/.linuxbrew/Cellar",
          "prefix": "/home/linuxbrew/.linuxbrew",
          "files": {
            "catalina": {
              "url": "https://linuxbrew.bintray.com/bottles/neovim-0.4.3_1.catalina.bottle.tar.gz",
              "sha256": "389ab254794ea04df8a106bf281c227c4fdee27c609d52951f32b9a0239031d6"
            },
            "mojave": {
              "url": "https://linuxbrew.bintray.com/bottles/neovim-0.4.3_1.mojave.bottle.tar.gz",
              "sha256": "fb6cc38c45be4650a4a750a314cec27f6f7643dc7c22a1f5abae347e1b39b388"
            },
            "high_sierra": {
              "url": "https://linuxbrew.bintray.com/bottles/neovim-0.4.3_1.high_sierra.bottle.tar.gz",
              "sha256": "b2f7450e005f4eb22bfaf650fe7741fa8629393a947b4dd48c9f91e7fc258113"
            },
            "x86_64_linux": {
              "url": "https://linuxbrew.bintray.com/bottles/neovim-0.4.3_1.x86_64_linux.bottle.tar.gz",
              "sha256": "1d9227bbfb72a42d49e9997adbb630169b677043ba993bfe2b02692eb5e7431b"
            }
          }
        }
      },
      "bash": {
        "version": "5.0.16",
        "bottle": {
          "cellar": "/home/linuxbrew/.linuxbrew/Cellar",
          "prefix": "/home/linuxbrew/.linuxbrew",
          "files": {
            "catalina": {
              "url": "https://linuxbrew.bintray.com/bottles/bash-5.0.16.catalina.bottle.tar.gz",
              "sha256": "a124202b5a5c0896ab93c8603eefae655ef622d34f9e15e4d4aa77f1cd314c1d"
            },
            "mojave": {
              "url": "https://linuxbrew.bintray.com/bottles/bash-5.0.16.mojave.bottle.tar.gz",
              "sha256": "dd9c4711dc1be6d54ea74143b224b21ab0d165fca090fbcb921efaa0c0bb2f12"
            },
            "high_sierra": {
              "url": "https://linuxbrew.bintray.com/bottles/bash-5.0.16.high_sierra.bottle.tar.gz",
              "sha256": "d8c36b430ff928f72b33bad666f1ae2170802e85b8b51594c953e583fd4f11be"
            },
            "x86_64_linux": {
              "url": "https://linuxbrew.bintray.com/bottles/bash-5.0.16.x86_64_linux.bottle.tar.gz",
              "sha256": "1fc3ce8baf22fd1f096affc47e68391f575ca6ac5c8e81c000783727c557fcb3"
            }
          }
        }
      },
      "zsh": {
        "version": "5.8",
        "bottle": {
          "cellar": "/home/linuxbrew/.linuxbrew/Cellar",
          "prefix": "/home/linuxbrew/.linuxbrew",
          "files": {
            "catalina": {
              "url": "https://linuxbrew.bintray.com/bottles/zsh-5.8.catalina.bottle.tar.gz",
              "sha256": "209d04a4d62f6162f1b6cf824d2c50b00b52cb812c04c1967e5b376573b5aef0"
            },
            "mojave": {
              "url": "https://linuxbrew.bintray.com/bottles/zsh-5.8.mojave.bottle.tar.gz",
              "sha256": "c5c35657637c97132efbaa0fd8e2add568aaa62adfe66e7d19f961f8e9506da9"
            },
            "high_sierra": {
              "url": "https://linuxbrew.bintray.com/bottles/zsh-5.8.high_sierra.bottle.tar.gz",
              "sha256": "029b8c6922f01bfd832dd0f4f940f99328d2495714c37c1dc7ef326d6fb1459e"
            },
            "x86_64_linux": {
              "url": "https://linuxbrew.bintray.com/bottles/zsh-5.8.x86_64_linux.bottle.tar.gz",
              "sha256": "76c6f1720e6253f9a9bb7549dfd52d9f95b402d640a859230da95b9a2c06322f"
            }
          }
        }
      },
      "nodejs": null,
      "rustup-init": {
        "version": "1.21.1",
        "bottle": {
          "cellar": ":any_skip_relocation",
          "prefix": "/home/linuxbrew/.linuxbrew",
          "files": {
            "catalina": {
              "url": "https://linuxbrew.bintray.com/bottles/rustup-init-1.21.1.catalina.bottle.tar.gz",
              "sha256": "a97694534834b8c87660c7d3ecf0cad6f030c39c50cd365c6a28ac167aaa4464"
            },
            "mojave": {
              "url": "https://linuxbrew.bintray.com/bottles/rustup-init-1.21.1.mojave.bottle.tar.gz",
              "sha256": "fad5c12bfcd7223aa445718df1427315fcc466df93c4c33f0629ecdf146191c8"
            },
            "high_sierra": {
              "url": "https://linuxbrew.bintray.com/bottles/rustup-init-1.21.1.high_sierra.bottle.tar.gz",
              "sha256": "6b52ab63b32993cfbcc9f5a2329b62c22501fbf9c4cb3b797b34d20d9641204d"
            },
            "x86_64_linux": {
              "url": "https://linuxbrew.bintray.com/bottles/rustup-init-1.21.1.x86_64_linux.bottle.tar.gz",
              "sha256": "db47f128116b376bbe1207760bfd43c765285b4dcf1b223659f7bdeed60925c9"
            }
          }
        }
      },
      "rustc-completion": {
        "version": "0.12.1",
        "bottle": false
      },
      "python3": null,
      "pipenv": {
        "version": "2018.11.26_4",
        "bottle": {
          "cellar": ":any_skip_relocation",
          "prefix": "/home/linuxbrew/.linuxbrew",
          "files": {
            "catalina": {
              "url": "https://linuxbrew.bintray.com/bottles/pipenv-2018.11.26_4.catalina.bottle.tar.gz",
              "sha256": "d8835620147f13436c15400db7d12d1d5b72769c7b67c5fe7f7a1d0e1dcbd88f"
            },
            "mojave": {
              "url": "https://linuxbrew.bintray.com/bottles/pipenv-2018.11.26_4.mojave.bottle.tar.gz",
              "sha256": "ccac725119c70e8f857e23d9448a61079697711aa5ad4a6a9b3b95ab5f747e5f"
            },
            "high_sierra": {
              "url": "https://linuxbrew.bintray.com/bottles/pipenv-2018.11.26_4.high_sierra.bottle.tar.gz",
              "sha256": "e58ee2436caed1a20c18b45067f1c28b987e542e7ebac17fe4d20f4e556f2b47"
            },
            "x86_64_linux": {
              "url": "https://linuxbrew.bintray.com/bottles/pipenv-2018.11.26_4.x86_64_linux.bottle.tar.gz",
              "sha256": "8cacda225c714fa2525591d0d99a31f2297e716943b6323418e7ee60e2161d21"
            }
          }
        }
      },
      "ruby": {
        "version": "2.7.1_3",
        "bottle": {
          "cellar": "/home/linuxbrew/.linuxbrew/Cellar",
          "prefix": "/home/linuxbrew/.linuxbrew",
          "files": {
            "catalina": {
              "url": "https://linuxbrew.bintray.com/bottles/ruby-2.7.1_3.catalina.bottle.tar.gz",
              "sha256": "7f5ed2afb15b25f9616b617ecca2ee376eb67cf6c105790df22221b7be9c1ef9"
            },
            "mojave": {
              "url": "https://linuxbrew.bintray.com/bottles/ruby-2.7.1_3.mojave.bottle.tar.gz",
              "sha256": "cc995a06e761acc8a807b040d8e7fe301902a4fc63d2beaaae40e04c710e7338"
            },
            "high_sierra": {
              "url": "https://linuxbrew.bintray.com/bottles/ruby-2.7.1_3.high_sierra.bottle.tar.gz",
              "sha256": "2605ad1636e40d747878a8df7d1ef51a15e58e70ce03510b9ea582c02a448e26"
            },
            "x86_64_linux": {
              "url": "https://linuxbrew.bintray.com/bottles/ruby-2.7.1_3.x86_64_linux.bottle.tar.gz",
              "sha256": "ff621c4d7d5024f9fa342c329b9c5063ab4194cf6bb22ca62ff6a224a6f05327"
            }
          }
        }
      }
    }
  },
  "system": {
    "linux": {
      "Ubuntu 18.04.4 LTS (bionic)": {
        "HOMEBREW_VERSION": "2.2.13",
        "HOMEBREW_PREFIX": "/home/linuxbrew/.linuxbrew",
        "Homebrew/linuxbrew-core": "601b74fcc2ed6ba07672c2412ac9490270096c5c",
        "GCC": "5.5.0"
      }
    }
  }
}
